lxfcode/__init__.py
lxfcode/instances.py
lxfcode/calcores/__init__.py
lxfcode/calcores/abc/__init__.py
lxfcode/calcores/abc/abcal.py
lxfcode/calcores/abc/abmoire.py
lxfcode/calcores/abc/aboptics.py
lxfcode/calcores/abc/abpshe.py
lxfcode/calcores/abc/self_types.py
lxfcode/calcores/absorption/__init__.py
lxfcode/calcores/absorption/absorption_cal.py
lxfcode/calcores/absorption/absorption_plot.py
lxfcode/calcores/bands/__init__.py
lxfcode/calcores/bands/bands_cal.py
lxfcode/calcores/bands/bands_plot.py
lxfcode/calcores/dos/__init__.py
lxfcode/calcores/dos/dos_cal.py
lxfcode/calcores/dos/dos_plot.py
lxfcode/calcores/filesop/__init__.py
lxfcode/calcores/filesop/fileman.py
lxfcode/calcores/filesop/fileread.py
lxfcode/calcores/filesop/filesave.py
lxfcode/calcores/hamiltonians/__init__.py
lxfcode/calcores/hamiltonians/conti_h.py
lxfcode/calcores/hamiltonians/ham_out.py
lxfcode/calcores/hamiltonians/klattices.py
lxfcode/calcores/hamiltonians/sk_potential.py
lxfcode/calcores/hamiltonians/tb_h.py
lxfcode/calcores/jdos/__init__.py
lxfcode/calcores/jdos/jdos_cal.py
lxfcode/calcores/jdos/jdos_plot.py
lxfcode/calcores/materials/__init__.py
lxfcode/calcores/materials/graphene.py
lxfcode/calcores/multical/__init__.py
lxfcode/calcores/multical/multicorecal.py
lxfcode/calcores/multical/raman_scan.py
lxfcode/calcores/opt_cond/__init__.py
lxfcode/calcores/opt_cond/optcond_cal.py
lxfcode/calcores/opt_cond/optcond_plot.py
lxfcode/calcores/pshe/__init__.py
lxfcode/calcores/pshe/cal.py
lxfcode/calcores/pshe/fitexp.py
lxfcode/calcores/pshe/shift.py
lxfcode/calcores/pubmeth/__init__.py
lxfcode/calcores/pubmeth/consts.py
lxfcode/calcores/pubmeth/gen_hams.py
lxfcode/calcores/pubmeth/methods.py
lxfcode/calcores/pubmeth/pointset.py
lxfcode/calcores/pubmeth/unit_conversion.py
lxfcode/calcores/raman/__init__.py
lxfcode/calcores/raman/raman_cal.py
lxfcode/calcores/raman/raman_plot.py
lxfcode/calcores/superlattices/__init__.py
lxfcode/calcores/superlattices/comm_stru.py
lxfcode-0.4.3.dist-info/LICENSE
lxfcode-0.4.3.dist-info/METADATA
lxfcode-0.4.3.dist-info/WHEEL
lxfcode-0.4.3.dist-info/top_level.txt
lxfcode-0.4.3.dist-info/RECORD
