Metadata-Version: 2.1
Name: lxfcode
Version: 0.4.3
Summary: 2D Materials calculations
Home-page: https://gitee.com/aoxv/py_code
Author: XiaofengLi
Author-email: aoxvli@qq.com
License: MIT
Classifier: License :: OSI Approved :: MIT License
Classifier: Programming Language :: Python
Classifier: Programming Language :: Python :: 3
Classifier: Programming Language :: Python :: 3.10
Classifier: Programming Language :: Python :: Implementation :: CPython
Classifier: Programming Language :: Python :: Implementation :: PyPy
Requires-Python: >=3.10.0
License-File: LICENSE
Requires-Dist: matplotlib
Requires-Dist: numpy
Requires-Dist: opencv-python
Requires-Dist: scipy
Requires-Dist: scikit-learn
Requires-Dist: pandas
